<?xml version="1.0" encoding="utf-8"?>
<weapon>
	<model>
		<weapon fireSound="Weapons/BlindingVenom"
				fireSoundCount="3"/>
	</model>
	<modifiers>
		<modifier>
			<effects>
				<meleeArmorPenetration add="0"/> <!-- %meleeArmorPenetration add armorPiercing=- -->
				<meleeDamage add="1"/> <!-- %meleeDamage add strength=3 -->
				<strengthDamage base="0"/>
			</effects>
		</modifier>
	</modifiers>
	<traits>
		<trait name="Blinding"/>
		<trait name="Melee"/>
		<trait name="Tyranids/MeleeDamage" requiredUpgrade="Tyranids/MeleeDamage"/>
		<trait name="Poisoned" rank="0"/>
	</traits>
</weapon>
